snapapi-0.1.9.dist-info/METADATA
snapapi-0.1.9.dist-info/WHEEL
snapapi-0.1.9.dist-info/entry_points.txt
snapapi-0.1.9.dist-info/licenses/LICENSE.md
snapapi/__init__.py
snapapi/applications.py
snapapi/cache.py
snapapi/codes.py
snapapi/exceptions.py
snapapi/logger.py
snapapi/model/__init__.py
snapapi/model/balance_inquiry.py
snapapi/model/bank_statement.py
snapapi/model/bill.py
snapapi/model/headers.py
snapapi/model/oauth2.py
snapapi/model/virtual_account/__init__.py
snapapi/model/virtual_account/inquiry.py
snapapi/model/virtual_account/payment.py
snapapi/responses.py
snapapi/routing.py
snapapi/security/__init__.py
snapapi/security/crypto.py
snapapi/security/oauth2.py
snapapi/tools.py
snapapi-0.1.9.dist-info/RECORD
