Metadata-Version: 2.1
Name: snapapi
Version: 0.1.9
Summary: Framework/tookit berbasis pydantic dan FastAPI untuk implementasi SNAP (Standar Nasional Open API Pembayaran) Indonesia
Keywords: snap,pg,payment gateway,bank,api
Author-Email: S Deta Harvianto <sdetta@gmail.com>
Classifier: Intended Audience :: Information Technology
Classifier: Intended Audience :: System Administrators
Classifier: Operating System :: OS Independent
Classifier: Programming Language :: Python :: 3
Classifier: Programming Language :: Python
Classifier: Topic :: Internet
Classifier: Topic :: Software Development :: Libraries :: Application Frameworks
Classifier: Topic :: Software Development :: Libraries :: Python Modules
Classifier: Topic :: Software Development :: Libraries
Classifier: Topic :: Software Development
Classifier: Typing :: Typed
Classifier: Development Status :: 4 - Beta
Classifier: Environment :: Web Environment
Classifier: Framework :: FastAPI
Classifier: Framework :: Pydantic
Classifier: Framework :: Pydantic :: 2
Classifier: Intended Audience :: Developers
Classifier: License :: OSI Approved :: MIT License
Classifier: Programming Language :: Python :: 3 :: Only
Classifier: Programming Language :: Python :: 3.8
Classifier: Programming Language :: Python :: 3.9
Classifier: Programming Language :: Python :: 3.10
Classifier: Programming Language :: Python :: 3.11
Classifier: Programming Language :: Python :: 3.12
Classifier: Programming Language :: Python :: 3.13
Classifier: Topic :: Internet :: WWW/HTTP :: HTTP Servers
Classifier: Topic :: Internet :: WWW/HTTP
Project-URL: Homepage, https://github.com/sdettahar/snapapi
Project-URL: Repository, https://github.com/sdettahar/snapapi
Project-URL: Issues, https://github.com/sdettahar/snapapi/issues
Requires-Python: >=3.8
Requires-Dist: starlette<0.47.0,>=0.40.0
Requires-Dist: pydantic<3.0.0,>=2.10.6
Requires-Dist: typing-extensions>=4.12.2
Requires-Dist: fastapi>=0.115.10
Requires-Dist: PyJWT>=2.9.0
Requires-Dist: pycryptodome>=3.21.0
Requires-Dist: ulid-py>=1.1.0
